thinkindicator/__init__.py
thinkindicator/__main__.py
thinkindicator/errors.py
thinkindicator/fan.py
thinkindicator/generate_icons.py
thinkindicator/indicator.py
thinkindicator/icons/0.png
thinkindicator/icons/1.png
thinkindicator/icons/2.png
thinkindicator/icons/3.png
thinkindicator/icons/4.png
thinkindicator/icons/5.png
thinkindicator/icons/6.png
thinkindicator/icons/7.png
thinkindicator/icons/A.png
thinkindicator/icons/D.png
thinkindicator/icons/F.png
thinkindicator-0.1.2.data/scripts/thinkindicator
thinkindicator-0.1.2.dist-info/LICENCE
thinkindicator-0.1.2.dist-info/METADATA
thinkindicator-0.1.2.dist-info/WHEEL
thinkindicator-0.1.2.dist-info/top_level.txt
thinkindicator-0.1.2.dist-info/RECORD
