Metadata-Version: 2.1
Name: thinkindicator
Version: 0.1.2
Summary: Tiny widget to control your ThinkPad's fan speed
Home-page: https://github.com/przemub/thinkindicator
Author: Przemysław Buczkowski
Author-email: prem@prem.moe
License: UNKNOWN
Platform: UNKNOWN
Classifier: Programming Language :: Python :: 3
Classifier: License :: OSI Approved :: MIT License
Classifier: Operating System :: POSIX :: Linux
Classifier: Environment :: X11 Applications :: GTK
Classifier: Intended Audience :: End Users/Desktop
Classifier: Topic :: System :: Hardware
Requires-Python: >=3.6
Requires-Dist: PyGObject
